carpentries/__init__.py
carpentries/__main__.py
carpentries/values.py
carpentries-0.0.3.dist-info/LICENSE
carpentries-0.0.3.dist-info/METADATA
carpentries-0.0.3.dist-info/WHEEL
carpentries-0.0.3.dist-info/entry_points.txt
carpentries-0.0.3.dist-info/top_level.txt
carpentries-0.0.3.dist-info/RECORD
