Metadata-Version: 2.1
Name: carpentries
Version: 0.0.3
Summary: Tools for the The Carpentries (Unofficial)
Home-page: https://github.com/tompollard/carpentries
Author: Tom Pollard
Author-email: tpollard@mit.edu
License: UNKNOWN
Keywords: The Carpentries,education,learning
Platform: UNKNOWN
Classifier: Development Status :: 3 - Alpha
Classifier: License :: OSI Approved :: MIT License
Classifier: Programming Language :: Python :: 3
Requires-Python: >=3.6, <4
License-File: LICENSE
